aiolifx/__init__.py
aiolifx/__main__.py
aiolifx/aiolifx.py
aiolifx/connection.py
aiolifx/message.py
aiolifx/msgtypes.py
aiolifx/products.py
aiolifx/unpack.py
aiolifx/update-products.py
haaiolifx-0.8.2.dist-info/LICENSE.txt
haaiolifx-0.8.2.dist-info/METADATA
haaiolifx-0.8.2.dist-info/WHEEL
haaiolifx-0.8.2.dist-info/entry_points.txt
haaiolifx-0.8.2.dist-info/top_level.txt
haaiolifx-0.8.2.dist-info/RECORD
