Metadata-Version: 2.1
Name: haaiolifx
Version: 0.8.2
Summary: API for local communication with LIFX devices over a LAN with asyncio.
Home-page: http://github.com/frawau/aiolifx
Author: François Wautier
Author-email: francois@wautier.eu
License: MIT
Keywords: lifx,light,automation
Classifier: License :: OSI Approved :: MIT License
Classifier: Programming Language :: Python :: 3
Requires-Python: >=3.4
License-File: LICENSE.txt
Requires-Dist: bitstring
Requires-Dist: ifaddr
